tiddlyserver/__init__.py
tiddlyserver/empty_with_tiddlyweb.html
tiddlyserver/git.py
tiddlyserver/make_reenable_plugin_downloads_plugin.py
tiddlyserver/server.py
tiddlyserver/tiddler_embedding.py
tiddlyserver/tiddler_hash.py
tiddlyserver/tiddler_serdes.py
tiddlyserver-0.2.0.dist-info/entry_points.txt
tiddlyserver-0.2.0.dist-info/LICENSE
tiddlyserver-0.2.0.dist-info/WHEEL
tiddlyserver-0.2.0.dist-info/METADATA
tiddlyserver-0.2.0.dist-info/RECORD
